kensu-datagalaxy-client/__init__.py
kensu-datagalaxy-client/api_client.py
kensu-datagalaxy-client/configuration.py
kensu-datagalaxy-client/rest.py
kensu-datagalaxy-client/api/__init__.py
kensu-datagalaxy-client/api/attributes_api.py
kensu-datagalaxy-client/api/authentication_api.py
kensu-datagalaxy-client/api/comments_api.py
kensu-datagalaxy-client/api/containers_api.py
kensu-datagalaxy-client/api/data_processing_api.py
kensu-datagalaxy-client/api/data_processing_item_api.py
kensu-datagalaxy-client/api/fields_api.py
kensu-datagalaxy-client/api/filtered_views_api.py
kensu-datagalaxy-client/api/glossary_api.py
kensu-datagalaxy-client/api/history_api.py
kensu-datagalaxy-client/api/image_api.py
kensu-datagalaxy-client/api/licenses_api.py
kensu-datagalaxy-client/api/links_api.py
kensu-datagalaxy-client/api/scim_users_api.py
kensu-datagalaxy-client/api/screens_api.py
kensu-datagalaxy-client/api/search_api.py
kensu-datagalaxy-client/api/sources_api.py
kensu-datagalaxy-client/api/structures_api.py
kensu-datagalaxy-client/api/tasks_api.py
kensu-datagalaxy-client/api/teams_api.py
kensu-datagalaxy-client/api/technologies_api.py
kensu-datagalaxy-client/api/usage_api.py
kensu-datagalaxy-client/api/users_api.py
kensu-datagalaxy-client/api/workspaces_api.py
kensu-datagalaxy-client/models/__init__.py
kensu-datagalaxy-client/models/access_data.py
kensu-datagalaxy-client/models/access_type.py
kensu-datagalaxy-client/models/additional_custom_attribute.py
kensu-datagalaxy-client/models/additional_custom_attribute_bulk.py
kensu-datagalaxy-client/models/all_types.py
kensu-datagalaxy-client/models/all_types_lower.py
kensu-datagalaxy-client/models/any_of_attribute_bulk_creation_body_default_value.py
kensu-datagalaxy-client/models/any_of_attribute_bulk_update_body_default_value.py
kensu-datagalaxy-client/models/any_of_attribute_creation_body_default_value.py
kensu-datagalaxy-client/models/any_of_attribute_default_value.py
kensu_datagalaxy_client-1.0.2.dist-info/METADATA
kensu_datagalaxy_client-1.0.2.dist-info/WHEEL
kensu_datagalaxy_client-1.0.2.dist-info/top_level.txt
kensu_datagalaxy_client-1.0.2.dist-info/RECORD
