Metadata-Version: 2.1
Name: kensu-datagalaxy-client
Version: 1.0.2
Summary: Developer API - DataGalaxy
Home-page: 
Author-email: 
Keywords: Swagger,Kensu,Developer API - DataGalaxy
Requires-Dist: urllib3 (>=1.15)
Requires-Dist: six (>=1.10)
Requires-Dist: certifi
Requires-Dist: python-dateutil
